[
      {
        "title": "สิ่งใดในข้อใดมีชีวิต?",
        "options": ["ก้อนหิน", "ต้นไม้", "ดิน", "น้ำ"],
        "answer": "2"
      },
      {
        "title": "สิ่งใดใช้หายใจได้?",
        "options": ["ปลา", "ดิน", "ก้อนหิน", "ทราย"],
        "answer": "1"
      },
      {
        "title": "ดอกไม้ต้องการอะไรในการเจริญเติบโต?",
        "options": ["ดิน", "น้ำ", "แสงแดด", "ทั้งหมดถูกต้อง"],
        "answer": "4"
      },
      {
        "title": "สัตว์ชนิดใดบินได้?",
        "options": ["สุนัข", "แมว", "นก", "ปลา"],
        "answer": "3"
      },
      {
        "title": "ต้นไม้ส่วนใดใช้ในการสังเคราะห์แสง?",
        "options": ["ราก", "ใบ", "ดอก", "ลำต้น"],
        "answer": "2"
      },
      {
        "title": "สิ่งใดคือแหล่งพลังงานหลักของโลก?",
        "options": ["ดวงจันทร์", "ดวงอาทิตย์", "น้ำ", "ไฟ"],
        "answer": "2"
      },
      {
        "title": "น้ำมีสถานะอะไรบ้าง?",
        "options": ["ของแข็ง", "ของเหลว", "ก๊าซ", "ถูกทุกข้อ"],
        "answer": "4"
      },
      {
        "title": "มนุษย์ต้องการอะไรในการหายใจ?",
        "options": ["คาร์บอนไดออกไซด์", "ออกซิเจน", "ไนโตรเจน", "ไฮโดรเจน"],
        "answer": "2"
      },
      {
        "title": "ผลไม้ชนิดใดมีรสเปรี้ยว?",
        "options": ["มะม่วงสุก", "มะนาว", "กล้วย", "แตงโม"],
        "answer": "2"
      },
      {
        "title": "สัตว์ชนิดใดอาศัยอยู่ในน้ำ?",
        "options": ["แมว", "ปลา", "นก", "ลิง"],
        "answer": "2"
      },
      {
        "title": "ดวงอาทิตย์ขึ้นทางทิศใด?",
        "options": ["ทิศเหนือ", "ทิศใต้", "ทิศตะวันออก", "ทิศตะวันตก"],
        "answer": "3"
      },
      {
        "title": "พืชสร้างอาหารเองได้โดยวิธีใด?",
        "options": ["การสังเคราะห์แสง", "การหายใจ", "การเดิน", "การดูดซึม"],
        "answer": "1"
      },
      {
        "title": "ส่วนใดของร่างกายที่ใช้ในการดมกลิ่น?",
        "options": ["ตา", "หู", "จมูก", "ปาก"],
        "answer": "3"
      },
      {
        "title": "สัตว์ชนิดใดกินพืชเป็นอาหาร?",
        "options": ["สิงโต", "กระต่าย", "เสือ", "แมว"],
        "answer": "2"
      },
      {
        "title": "ผลไม้ชนิดใดมีเมล็ดมาก?",
        "options": ["มะม่วง", "แตงโม", "กล้วย", "มังคุด"],
        "answer": "2"
      },
      {
        "title": "ฤดูฝน เรามักพบสิ่งใด?",
        "options": ["หิมะ", "แดดจัด", "ฝนตก", "หมอก"],
        "answer": "3"
      },
      {
        "title": "มนุษย์กินอาหารเพื่ออะไร?",
        "options": ["สนุก", "เจริญเติบโต", "นอนหลับ", "เล่น"],
        "answer": "2"
      },
      {
        "title": "สิ่งใดไม่ใช่สัตว์?",
        "options": ["แมว", "ปลาหมึก", "ก้อนหิน", "นก"],
        "answer": "3"
      },
      {
        "title": "พืชส่วนใดที่เรามักกิน?",
        "options": ["ใบ", "ดอก", "ราก", "ทั้งหมดถูกต้อง"],
        "answer": "4"
      },
      {
        "title": "สัตว์ใดเลี้ยงลูกด้วยนม?",
        "options": ["นก", "ปลา", "แมว", "ไก่"],
        "answer": "3"
    }
]
  